mathmodel/__init__.py
mathmodel/pytime.py
mathmodel/utils.py
mathmodel/dataset/__init__.py
mathmodel/dataset/base.py
mathmodel/dataset/utils/__init__.py
mathmodel/quant/__init__.py
mathmodel/quant/cost_calculation.py
mathmodel/statisticmodel/__init__.py
mathmodel-0.1.23.4.dist-info/DESCRIPTION.rst
mathmodel-0.1.23.4.dist-info/METADATA
mathmodel-0.1.23.4.dist-info/RECORD
mathmodel-0.1.23.4.dist-info/WHEEL
mathmodel-0.1.23.4.dist-info/metadata.json
mathmodel-0.1.23.4.dist-info/top_level.txt
