Metadata-Version: 2.0
Name: mathmodel
Version: 0.1.23.4
Summary: mathmodel REST API access modules
Home-page: https://github.com/h-WAVES/Mathmodel
Author: Waves
Author-email: hhtnan@163.com
Maintainer: Waves
Maintainer-email: hhtnan@163.com
License: MIT
Keywords: mathmodel,Model,alg,mathematical,mcm
Platform: UNKNOWN
Classifier: Programming Language :: Python :: 3
Classifier: Intended Audience :: Developers
Classifier: Intended Audience :: Information Technology
Classifier: Intended Audience :: System Administrators
Classifier: License :: OSI Approved :: MIT License
Classifier: Operating System :: OS Independent
Classifier: Topic :: Software Development :: Libraries :: Python Modules
Classifier: Topic :: System :: Systems Administration
Classifier: Topic :: Internet
Requires-Python: >=3.4
License-File: LICENSE
Requires-Dist: numpy (>=1.18.3)
Requires-Dist: pipreqs (>=0.4.10)
